{
  "extends": ["tslint:latest", "tslint-config-prettier"],
  "rules": {
    "array-type": [true, "array"],
    "arrow-return-shorthand": [true, "multiline"],
    "class-name": true,
    "interface-name": [true, "never-prefix"],
    "interface-over-type-literal": false,
    "max-classes-per-file": false,
    "member-access": [true, "no-public"],
    "member-ordering": [
      true,
      {
        "order": [
          "public-static-field",
          "public-static-method",
          "protected-static-field",
          "protected-static-method",
          "private-static-field",
          "private-static-method",
          "public-instance-field",
          "protected-instance-field",
          "private-instance-field",
          "public-constructor",
          "protected-constructor",
          "private-constructor",
          "public-instance-method",
          "protected-instance-method",
          "private-instance-method"
        ]
      }
    ],
    "no-angle-bracket-type-assertion": true,
    "no-any": false,
    "no-arg": true,
    "no-conditional-assignment": true,
    "no-console": [true, "info", "log"],
    "no-construct": true,
    "no-debugger": true,
    "no-default-export": true,
    "no-duplicate-super": true,
    "no-duplicate-variable": true,
    "no-empty": true,
    "no-empty-interface": false,
    "no-eval": true,
    "no-implicit-dependencies": [true, "dev"],
    "no-mergeable-namespace": true,
    "no-object-literal-type-assertion": false,
    "no-require-imports": false,
    "no-var-keyword": true,
    "no-var-requires": true,
    "no-shadowed-variable": false,
    "no-string-literal": false,
    "no-unsafe-finally": true,
    "no-unnecessary-initializer": true,
    "no-unused-variable": false,
    "object-literal-key-quotes": [true, "as-needed"],
    "object-literal-shorthand": true,
    "object-literal-sort-keys": true,
    "one-variable-per-declaration": [true, "ignore-for-loop"],
    "ordered-imports": true,
    "prefer-const": true,
    "prefer-function-over-method": [true, "allow-public", "allow-protected"],
    "prefer-method-signature": true,
    "prefer-object-spread": true,
    "switch-default": true,
    "triple-equals": true,

    "variable-name": [true, "allow-leading-underscore", "allow-pascal-case"]
  }
}
